jlogs/__init__.py
jlogs/cli.py
jlogs/jlogs.py
jlogs-0.1.0.dist-info/METADATA
jlogs-0.1.0.dist-info/WHEEL
jlogs-0.1.0.dist-info/entry_points.txt
jlogs-0.1.0.dist-info/top_level.txt
jlogs-0.1.0.dist-info/RECORD
